tqdj/__init__.py
tqdj/_monitor.py
tqdj/player.py
tqdj/std.py
tqdj/utils.py
tqdj/music/cruise.wav
tqdj/music/jazzy.wav
tqdj/music/mondays.wav
tqdj/music/paradise.wav
tqdj/music/time.wav
tqdj-0.0.2.dist-info/LICENSE
tqdj-0.0.2.dist-info/METADATA
tqdj-0.0.2.dist-info/WHEEL
tqdj-0.0.2.dist-info/top_level.txt
tqdj-0.0.2.dist-info/RECORD
