Metadata-Version: 2.1
Name: tqdj
Version: 0.0.2
Summary: A progress bar that plays lofi music
Home-page: https://github.com/sri-rad/tqdj
Author: Srihari Radhakrishna
Author-email: rsrihari95@gmail.com
License: UNKNOWN
Platform: UNKNOWN
Classifier: Programming Language :: Python :: 3
Classifier: License :: OSI Approved :: MIT License
Classifier: Operating System :: OS Independent
Requires-Python: >=3.6
Requires-Dist: simpleaudio
